setup.cfg
setup.py
partlycloudy/__init__.py
partlycloudy.egg-info/PKG-INFO
partlycloudy.egg-info/SOURCES.txt
partlycloudy.egg-info/dependency_links.txt
partlycloudy.egg-info/requires.txt
partlycloudy.egg-info/top_level.txt